[{
  "_id": {
    "$oid": "6658f98aa427f205988bfe79"
  },
  "name": "טרי",
  "description": "",
  "createdAt": {
    "$date": "2024-05-30T22:11:22.798Z"
  },
  "updatedAt": {
    "$date": "2024-05-30T22:11:22.798Z"
  },
  "__v": 0
},
{
  "_id": {
    "$oid": "6658f998a427f205988bfe7c"
  },
  "name": "בשרי",
  "description": "",
  "createdAt": {
    "$date": "2024-05-30T22:11:36.794Z"
  },
  "updatedAt": {
    "$date": "2024-05-30T22:11:36.794Z"
  },
  "__v": 0
},
{
  "_id": {
    "$oid": "6658f99fa427f205988bfe7f"
  },
  "name": "פרווה ",
  "description": "",
  "createdAt": {
    "$date": "2024-05-30T22:11:43.484Z"
  },
  "updatedAt": {
    "$date": "2024-05-30T22:11:43.484Z"
  },
  "__v": 0
}]